django_workos-0.9.0.dist-info/licenses/LICENSE
workos_login/__init__.py
workos_login/admin.py
workos_login/admin_site.py
workos_login/apps.py
workos_login/conf.py
workos_login/exceptions.py
workos_login/forms.py
workos_login/models.py
workos_login/signals.py
workos_login/tests.py
workos_login/urls.py
workos_login/utils.py
workos_login/views.py
workos_login/migrations/0001_initial.py
workos_login/migrations/0002_auto_20220803_2242.py
workos_login/migrations/0003_loginrule_jit_username_format.py
workos_login/migrations/0004_rename_jit_attributes_loginrule_saved_attributes.py
workos_login/migrations/0005_remove_loginrule_jit_username_format_userlogin_rule.py
workos_login/migrations/0006_loginrule_jit_creation_type.py
workos_login/migrations/0007_auto_20230227_0020.py
workos_login/migrations/0008_remove_loginrule_jit_creation_and_more.py
workos_login/migrations/0009_alter_loginrule_method.py
workos_login/migrations/0010_loginrule_environment_alter_loginrule_method.py
workos_login/migrations/__init__.py
workos_login/migrations/__pycache__/0001_initial.cpython-310.pyc
workos_login/migrations/__pycache__/0001_initial.cpython-312.pyc
workos_login/migrations/__pycache__/0002_auto_20220803_2242.cpython-310.pyc
workos_login/migrations/__pycache__/0002_auto_20220803_2242.cpython-312.pyc
workos_login/migrations/__pycache__/0003_loginrule_jit_username_format.cpython-310.pyc
workos_login/migrations/__pycache__/0003_loginrule_jit_username_format.cpython-312.pyc
workos_login/migrations/__pycache__/0003_remove_userlogin_mfa_enabled_userlogin_mfa_type_and_more.cpython-310.pyc
workos_login/migrations/__pycache__/0004_alter_loginrule_email_regex_and_more.cpython-310.pyc
workos_login/migrations/__pycache__/0004_rename_jit_attributes_loginrule_saved_attributes.cpython-310.pyc
workos_login/migrations/__pycache__/0004_rename_jit_attributes_loginrule_saved_attributes.cpython-312.pyc
workos_login/migrations/__pycache__/0005_loginrule_jit_attributes.cpython-310.pyc
django_workos-0.9.0.dist-info/METADATA
django_workos-0.9.0.dist-info/WHEEL
django_workos-0.9.0.dist-info/top_level.txt
django_workos-0.9.0.dist-info/RECORD
