Metadata-Version: 2.4
Name: django-workos
Version: 0.9.0
Summary: Enabling SSO, MFA and passwordless login for Django projects by using WorkOS.
License: BSD 3-Clause License
Project-URL: Homepage, https://github.com/surefyresystems/django-workos
Keywords: django,sso,workos,mfa
Classifier: Framework :: Django
Classifier: Programming Language :: Python :: 3
Requires-Python: >=3.7
License-File: LICENSE
Requires-Dist: workos==5.23
Requires-Dist: requests_oauthlib==2.0.0
Dynamic: license-file
